{
  "hash": "69d7f226",
  "configHash": "a3b77a99",
  "lockfileHash": "02a1457e",
  "browserHash": "d10b7333",
  "optimized": {
    "react-dom/client": {
      "src": "../../node_modules/react-dom/client.js",
      "file": "react-dom_client.js",
      "fileHash": "ff3541c6",
      "needsInterop": true
    },
    "react": {
      "src": "../../node_modules/react/index.js",
      "file": "react.js",
      "fileHash": "8d85a886",
      "needsInterop": true
    },
    "@fortawesome/react-fontawesome": {
      "src": "../../node_modules/@fortawesome/react-fontawesome/index.es.js",
      "file": "@fortawesome_react-fontawesome.js",
      "fileHash": "43e0086d",
      "needsInterop": false
    },
    "@fortawesome/free-solid-svg-icons": {
      "src": "../../node_modules/@fortawesome/free-solid-svg-icons/index.mjs",
      "file": "@fortawesome_free-solid-svg-icons.js",
      "fileHash": "2875d99c",
      "needsInterop": false
    },
    "react-beautiful-dnd": {
      "src": "../../node_modules/react-beautiful-dnd/dist/react-beautiful-dnd.esm.js",
      "file": "react-beautiful-dnd.js",
      "fileHash": "8d2f3ce6",
      "needsInterop": false
    },
    "react-timer-hook": {
      "src": "../../node_modules/react-timer-hook/dist/index.js",
      "file": "react-timer-hook.js",
      "fileHash": "7723dbfc",
      "needsInterop": true
    }
  },
  "chunks": {
    "chunk-HCGKX5ED": {
      "file": "chunk-HCGKX5ED.js"
    },
    "chunk-BBQBRKL6": {
      "file": "chunk-BBQBRKL6.js"
    },
    "chunk-WNPTCGAH": {
      "file": "chunk-WNPTCGAH.js"
    },
    "chunk-5WRI5ZAA": {
      "file": "chunk-5WRI5ZAA.js"
    }
  }
}